Metadata-Version: 1.0
Name: torrent-bencode
Version: 0.2
Summary: An implementation of Bencode encoding in Python 3
Home-page: https://github.com/kazimirovic/bencode
Author: kazimirovic
Author-email: kazimirovic@protonmail.com
License: MIT
Platform: UNKNOWN
